corptools/__init__.py
corptools/admin.py
corptools/app_settings.py
corptools/apps.py
corptools/auth_hooks.py
corptools/forms.py
corptools/managers.py
corptools/providers.py
corptools/signals.py
corptools/urls.py
corptools/validators.py
corptools/views.py
corptools/api/__init__.py
corptools/api/decorators.py
corptools/api/helpers.py
corptools/api/schema.py
corptools/api/character/__init__.py
corptools/api/character/assets.py
corptools/api/character/at_a_glance.py
corptools/api/character/clones.py
corptools/api/character/finances.py
corptools/api/character/industry.py
corptools/api/character/interactions.py
corptools/api/character/list.py
corptools/api/character/mining.py
corptools/api/character/refresh.py
corptools/api/character/roles.py
corptools/api/character/skills.py
corptools/api/character/status.py
corptools/api/core/__init__.py
corptools/api/core/menu.py
corptools/api/core/search.py
corptools/api/corporation/__init__.py
corptools/api/corporation/assets.py
corptools/api/corporation/at_a_glance.py
corptools/api/corporation/dashboards.py
corptools/api/corporation/finances.py
corptools/api/corporation/list.py
corptools/api/corporation/mining.py
corptools/api/corporation/status.py
corptools/api/corporation/structures.py
corptools/api/extras/__init__.py
corptools/api/extras/asset_pinger.py
corptools/api/extras/clone_deaths.py
corptools/api/extras/fittings.py
corptools/api/extras/testing.py
corptools/cogs/locate.py
corptools/cogs/routes.py
corptools/cogs/where.py
corptools/constants/__init__.py
corptools/constants/tasks.py
corptools/constants/types.py
corptools/locale/de/LC_MESSAGES/django.mo
corptools/locale/de/LC_MESSAGES/django.po
corptools/locale/en/LC_MESSAGES/django.mo
corptools/locale/en/LC_MESSAGES/django.po
corptools/locale/es/LC_MESSAGES/django.mo
corptools/locale/es/LC_MESSAGES/django.po
corptools/locale/fr_FR/LC_MESSAGES/django.mo
corptools/locale/fr_FR/LC_MESSAGES/django.po
corptools/locale/it_IT/LC_MESSAGES/django.mo
allianceauth_corp_tools_zoo-0.0.3.dist-info/METADATA
allianceauth_corp_tools_zoo-0.0.3.dist-info/WHEEL
allianceauth_corp_tools_zoo-0.0.3.dist-info/licenses/LICENSE
allianceauth_corp_tools_zoo-0.0.3.dist-info/RECORD
