Metadata-Version: 2.4
Name: allianceauth-corp-tools-zoo
Version: 0.0.3
Summary: Corp Level Toolbox for directors and CEO's
Project-URL: Homepage, https://github.com/guarzo/allianceauth-corp-tools-zoo
Project-URL: Source, https://github.com/guarzo/allianceauth-corp-tools-zoo
Project-URL: Tracker, https://github.com/guarzo/allianceauth-corp-tools-zoo/issues
Author-email: AaronKable <aaronkable@gmail.com>
License: Copyright 2023 Aaron Kable
License-File: LICENSE
Keywords: allianceauth,eveonline
Classifier: Environment :: Web Environment
Classifier: Framework :: Celery
Classifier: Framework :: Django
Classifier: Framework :: Django :: 4.0
Classifier: Framework :: Django :: 4.2
Classifier: Intended Audience :: Developers
Classifier: License :: OSI Approved :: MIT License
Classifier: Operating System :: OS Independent
Classifier: Programming Language :: Python
Classifier: Programming Language :: Python :: 3 :: Only
Classifier: Programming Language :: Python :: 3.8
Classifier: Programming Language :: Python :: 3.9
Classifier: Programming Language :: Python :: 3.10
Classifier: Programming Language :: Python :: 3.11
Classifier: Programming Language :: Python :: 3.12
Classifier: Programming Language :: Python :: Implementation :: CPython
Classifier: Topic :: Internet :: WWW/HTTP
Classifier: Topic :: Internet :: WWW/HTTP :: Dynamic Content
Requires-Python: >=3.8
Requires-Dist: allianceauth<6,>=4.6.1
Requires-Dist: django-model-utils
Requires-Dist: django-ninja<2,>=1.0.1
Requires-Dist: networkx
Requires-Dist: pydantic<3,>=2.12.3
Provides-Extra: test
Requires-Dist: allianceauth-securegroups; extra == 'test'
